{
  "model": "sequence_dynamic_prototype",
  "source": "amazon_movies_and_tv",
  "seed": 2026,
  "select_metric": "NDCG@10",
  "best_beta_sem": 0.0,
  "best_beta_dyn": 0.02,
  "best_metric": 0.26192617416381836,
  "best_row": {
    "model": "sequence_dynamic_prototype",
    "stage": "source_val",
    "source": "amazon_movies_and_tv",
    "target": "",
    "seed": 2026,
    "semantic_checkpoint": "artifacts\\checkpoints\\semantic_final\\semantic_amazon_movies_and_tv_seed2026.pt",
    "prototype_bank": "artifacts\\prototypes\\sequence_dynamic_amazon_movies_and_tv_M128_seed2026.pt",
    "candidate_dynamic_source": "artifacts\\checkpoints\\continuous_dynamic\\semantic_conditioned_prior_enhanced_amazon_movies_and_tv_seed2026.pt::enhanced",
    "ranking_mode": "sampled",
    "eval_negatives": 100,
    "Recall@10": 0.3811128910247853,
    "Recall@20": 0.423547145463445,
    "NDCG@10": 0.26192617416381836,
    "NDCG@20": 0.27275896072387695,
    "MRR@10": 0.2248038649559021,
    "MRR@20": 0.22783209383487701,
    "tie_case_ratio": 0.46071953010279,
    "all_equal_ratio": 0.0,
    "avg_tie_items": 13.50676367196191,
    "num_eval_users": 179784,
    "tie_policy": "worst",
    "beta_sem": 0.0,
    "beta_dyn": 0.02,
    "top_m": 16,
    "temperature": 0.05,
    "semantic_score_norm": "zscore",
    "prototype_score_norm": "zscore",
    "dynamic_score_norm": "zscore",
    "eval_elapsed_sec": 35.69693207740784,
    "eval_users_per_sec": 5036.3991955987485
  },
  "semantic_checkpoint": "artifacts\\checkpoints\\semantic_final\\semantic_amazon_movies_and_tv_seed2026.pt",
  "prototype_bank": "artifacts\\prototypes\\sequence_dynamic_amazon_movies_and_tv_M128_seed2026.pt",
  "candidate_dynamic_source": "artifacts\\checkpoints\\continuous_dynamic\\semantic_conditioned_prior_enhanced_amazon_movies_and_tv_seed2026.pt::enhanced",
  "top_m": 16,
  "temperature": 0.05,
  "history": [
    {
      "model": "sequence_dynamic_prototype",
      "stage": "source_val",
      "source": "amazon_movies_and_tv",
      "target": "",
      "seed": 2026,
      "semantic_checkpoint": "artifacts\\checkpoints\\semantic_final\\semantic_amazon_movies_and_tv_seed2026.pt",
      "prototype_bank": "artifacts\\prototypes\\sequence_dynamic_amazon_movies_and_tv_M128_seed2026.pt",
      "candidate_dynamic_source": "artifacts\\checkpoints\\continuous_dynamic\\semantic_conditioned_prior_enhanced_amazon_movies_and_tv_seed2026.pt::enhanced",
      "ranking_mode": "sampled",
      "eval_negatives": 100,
      "Recall@10": 0.3804676723178926,
      "Recall@20": 0.4231911627286077,
      "NDCG@10": 0.2616097033023834,
      "NDCG@20": 0.2725223898887634,
      "MRR@10": 0.22457639873027802,
      "MRR@20": 0.22763031721115112,
      "tie_case_ratio": 0.4617707916166066,
      "all_equal_ratio": 0.0,
      "avg_tie_items": 13.518433230988297,
      "num_eval_users": 179784,
      "tie_policy": "worst",
      "beta_sem": 0.0,
      "beta_dyn": 0.0,
      "top_m": 16,
      "temperature": 0.05,
      "semantic_score_norm": "zscore",
      "prototype_score_norm": "zscore",
      "dynamic_score_norm": "zscore",
      "eval_elapsed_sec": 33.27621555328369,
      "eval_users_per_sec": 5402.777840290163,
      "semantic_raw_mean": -0.0828852429986,
      "semantic_raw_std": 2.8880491256713867,
      "semantic_raw_min": -9.274948120117188,
      "semantic_raw_max": 9.265499114990234,
      "semantic_raw_row_std_mean": 2.421011209487915,
      "semantic_raw_row_std_min": 1.190649390220642,
      "semantic_raw_row_std_max": 3.9857351779937744,
      "semantic_mean": 2.9507249976745697e-09,
      "semantic_std": 1.0,
      "semantic_min": -3.565526008605957,
      "semantic_max": 5.857654094696045,
      "semantic_row_std_mean": 1.0,
      "semantic_row_std_min": 0.9999998807907104,
      "semantic_row_std_max": 1.0000001192092896,
      "prototype_semantic_mean": 4.367072747868406e-08,
      "prototype_semantic_std": 0.9999999403953552,
      "prototype_semantic_min": -3.526216506958008,
      "prototype_semantic_max": 4.86756706237793,
      "prototype_semantic_row_std_mean": 1.0,
      "prototype_semantic_row_std_min": 0.9999998211860657,
      "prototype_semantic_row_std_max": 1.0000001192092896,
      "prototype_dynamic_mean": 1.1802899768653674e-09,
      "prototype_dynamic_std": 1.0,
      "prototype_dynamic_min": -4.700531005859375,
      "prototype_dynamic_max": 4.842283725738525,
      "prototype_dynamic_row_std_mean": 1.0,
      "prototype_dynamic_row_std_min": 0.9999998807907104,
      "prototype_dynamic_row_std_max": 1.0000001192092896,
      "prototype_confidence_mean": 0.16481918096542358,
      "prototype_confidence_std": 0.15314486622810364,
      "prototype_confidence_min": 0.010194540023803711,
      "prototype_confidence_max": 0.7063370943069458,
      "prototype_top_similarity_mean": 0.9271144866943359,
      "prototype_top_similarity_std": 0.04925479367375374,
      "prototype_top_similarity_min": 0.8028268218040466,
      "prototype_top_similarity_max": 0.999779224395752,
      "fused_mean": 2.9507249976745697e-09,
      "fused_std": 1.0,
      "fused_min": -3.565526008605957,
      "fused_max": 5.857654094696045,
      "fused_row_std_mean": 1.0,
      "fused_row_std_min": 0.9999998807907104,
      "fused_row_std_max": 1.0000001192092896
    },
    {
      "model": "sequence_dynamic_prototype",
      "stage": "source_val",
      "source": "amazon_movies_and_tv",
      "target": "",
      "seed": 2026,
      "semantic_checkpoint": "artifacts\\checkpoints\\semantic_final\\semantic_amazon_movies_and_tv_seed2026.pt",
      "prototype_bank": "artifacts\\prototypes\\sequence_dynamic_amazon_movies_and_tv_M128_seed2026.pt",
      "candidate_dynamic_source": "artifacts\\checkpoints\\continuous_dynamic\\semantic_conditioned_prior_enhanced_amazon_movies_and_tv_seed2026.pt::enhanced",
      "ranking_mode": "sampled",
      "eval_negatives": 100,
      "Recall@10": 0.3811128910247853,
      "Recall@20": 0.423547145463445,
      "NDCG@10": 0.26192617416381836,
      "NDCG@20": 0.27275896072387695,
      "MRR@10": 0.2248038649559021,
      "MRR@20": 0.22783209383487701,
      "tie_case_ratio": 0.46071953010279,
      "all_equal_ratio": 0.0,
      "avg_tie_items": 13.50676367196191,
      "num_eval_users": 179784,
      "tie_policy": "worst",
      "beta_sem": 0.0,
      "beta_dyn": 0.02,
      "top_m": 16,
      "temperature": 0.05,
      "semantic_score_norm": "zscore",
      "prototype_score_norm": "zscore",
      "dynamic_score_norm": "zscore",
      "eval_elapsed_sec": 35.69693207740784,
      "eval_users_per_sec": 5036.3991955987485
    },
    {
      "model": "sequence_dynamic_prototype",
      "stage": "source_val",
      "source": "amazon_movies_and_tv",
      "target": "",
      "seed": 2026,
      "semantic_checkpoint": "artifacts\\checkpoints\\semantic_final\\semantic_amazon_movies_and_tv_seed2026.pt",
      "prototype_bank": "artifacts\\prototypes\\sequence_dynamic_amazon_movies_and_tv_M128_seed2026.pt",
      "candidate_dynamic_source": "artifacts\\checkpoints\\continuous_dynamic\\semantic_conditioned_prior_enhanced_amazon_movies_and_tv_seed2026.pt::enhanced",
      "ranking_mode": "sampled",
      "eval_negatives": 100,
      "Recall@10": 0.3810683931829306,
      "Recall@20": 0.4240032483424554,
      "NDCG@10": 0.2618361711502075,
      "NDCG@20": 0.27280792593955994,
      "MRR@10": 0.22468900680541992,
      "MRR@20": 0.22776225209236145,
      "tie_case_ratio": 0.4595458995238731,
      "all_equal_ratio": 0.0,
      "avg_tie_items": 13.498131090642104,
      "num_eval_users": 179784,
      "tie_policy": "worst",
      "beta_sem": 0.0,
      "beta_dyn": 0.05,
      "top_m": 16,
      "temperature": 0.05,
      "semantic_score_norm": "zscore",
      "prototype_score_norm": "zscore",
      "dynamic_score_norm": "zscore",
      "eval_elapsed_sec": 35.68733072280884,
      "eval_users_per_sec": 5037.754193397678
    },
    {
      "model": "sequence_dynamic_prototype",
      "stage": "source_val",
      "source": "amazon_movies_and_tv",
      "target": "",
      "seed": 2026,
      "semantic_checkpoint": "artifacts\\checkpoints\\semantic_final\\semantic_amazon_movies_and_tv_seed2026.pt",
      "prototype_bank": "artifacts\\prototypes\\sequence_dynamic_amazon_movies_and_tv_M128_seed2026.pt",
      "candidate_dynamic_source": "artifacts\\checkpoints\\continuous_dynamic\\semantic_conditioned_prior_enhanced_amazon_movies_and_tv_seed2026.pt::enhanced",
      "ranking_mode": "sampled",
      "eval_negatives": 100,
      "Recall@10": 0.38082365505272997,
      "Recall@20": 0.42408111956570105,
      "NDCG@10": 0.2614022493362427,
      "NDCG@20": 0.2724536955356598,
      "MRR@10": 0.22420327365398407,
      "MRR@20": 0.2272973507642746,
      "tie_case_ratio": 0.45945690384016374,
      "all_equal_ratio": 0.0,
      "avg_tie_items": 13.492808036310239,
      "num_eval_users": 179784,
      "tie_policy": "worst",
      "beta_sem": 0.0,
      "beta_dyn": 0.08,
      "top_m": 16,
      "temperature": 0.05,
      "semantic_score_norm": "zscore",
      "prototype_score_norm": "zscore",
      "dynamic_score_norm": "zscore",
      "eval_elapsed_sec": 35.987128257751465,
      "eval_users_per_sec": 4995.786235354174
    },
    {
      "model": "sequence_dynamic_prototype",
      "stage": "source_val",
      "source": "amazon_movies_and_tv",
      "target": "",
      "seed": 2026,
      "semantic_checkpoint": "artifacts\\checkpoints\\semantic_final\\semantic_amazon_movies_and_tv_seed2026.pt",
      "prototype_bank": "artifacts\\prototypes\\sequence_dynamic_amazon_movies_and_tv_M128_seed2026.pt",
      "candidate_dynamic_source": "artifacts\\checkpoints\\continuous_dynamic\\semantic_conditioned_prior_enhanced_amazon_movies_and_tv_seed2026.pt::enhanced",
      "ranking_mode": "sampled",
      "eval_negatives": 100,
      "Recall@10": 0.3810016464201486,
      "Recall@20": 0.42438147999822007,
      "NDCG@10": 0.26114314794540405,
      "NDCG@20": 0.2722192704677582,
      "MRR@10": 0.22381114959716797,
      "MRR@20": 0.22690853476524353,
      "tie_case_ratio": 0.45940128153784543,
      "all_equal_ratio": 0.0,
      "avg_tie_items": 13.490894629110489,
      "num_eval_users": 179784,
      "tie_policy": "worst",
      "beta_sem": 0.0,
      "beta_dyn": 0.1,
      "top_m": 16,
      "temperature": 0.05,
      "semantic_score_norm": "zscore",
      "prototype_score_norm": "zscore",
      "dynamic_score_norm": "zscore",
      "eval_elapsed_sec": 35.63382649421692,
      "eval_users_per_sec": 5045.318386707009
    },
    {
      "model": "sequence_dynamic_prototype",
      "stage": "source_val",
      "source": "amazon_movies_and_tv",
      "target": "",
      "seed": 2026,
      "semantic_checkpoint": "artifacts\\checkpoints\\semantic_final\\semantic_amazon_movies_and_tv_seed2026.pt",
      "prototype_bank": "artifacts\\prototypes\\sequence_dynamic_amazon_movies_and_tv_M128_seed2026.pt",
      "candidate_dynamic_source": "artifacts\\checkpoints\\continuous_dynamic\\semantic_conditioned_prior_enhanced_amazon_movies_and_tv_seed2026.pt::enhanced",
      "ranking_mode": "sampled",
      "eval_negatives": 100,
      "Recall@10": 0.3806345392248476,
      "Recall@20": 0.4242201753214969,
      "NDCG@10": 0.2598258852958679,
      "NDCG@20": 0.27095603942871094,
      "MRR@10": 0.22222469747066498,
      "MRR@20": 0.22533778846263885,
      "tie_case_ratio": 0.45912317002625375,
      "all_equal_ratio": 0.0,
      "avg_tie_items": 13.489064655364215,
      "num_eval_users": 179784,
      "tie_policy": "worst",
      "beta_sem": 0.0,
      "beta_dyn": 0.15,
      "top_m": 16,
      "temperature": 0.05,
      "semantic_score_norm": "zscore",
      "prototype_score_norm": "zscore",
      "dynamic_score_norm": "zscore",
      "eval_elapsed_sec": 35.66859769821167,
      "eval_users_per_sec": 5040.400004539957
    },
    {
      "model": "sequence_dynamic_prototype",
      "stage": "source_val",
      "source": "amazon_movies_and_tv",
      "target": "",
      "seed": 2026,
      "semantic_checkpoint": "artifacts\\checkpoints\\semantic_final\\semantic_amazon_movies_and_tv_seed2026.pt",
      "prototype_bank": "artifacts\\prototypes\\sequence_dynamic_amazon_movies_and_tv_M128_seed2026.pt",
      "candidate_dynamic_source": "artifacts\\checkpoints\\continuous_dynamic\\semantic_conditioned_prior_enhanced_amazon_movies_and_tv_seed2026.pt::enhanced",
      "ranking_mode": "sampled",
      "eval_negatives": 100,
      "Recall@10": 0.3794442219552352,
      "Recall@20": 0.42358608107506784,
      "NDCG@10": 0.25781771540641785,
      "NDCG@20": 0.2690942585468292,
      "MRR@10": 0.21997393667697906,
      "MRR@20": 0.22313019633293152,
      "tie_case_ratio": 0.45894517865883505,
      "all_equal_ratio": 0.0,
      "avg_tie_items": 13.491706714724335,
      "num_eval_users": 179784,
      "tie_policy": "worst",
      "beta_sem": 0.0,
      "beta_dyn": 0.2,
      "top_m": 16,
      "temperature": 0.05,
      "semantic_score_norm": "zscore",
      "prototype_score_norm": "zscore",
      "dynamic_score_norm": "zscore",
      "eval_elapsed_sec": 35.6338906288147,
      "eval_users_per_sec": 5045.309306040833
    },
    {
      "model": "sequence_dynamic_prototype",
      "stage": "source_val",
      "source": "amazon_movies_and_tv",
      "target": "",
      "seed": 2026,
      "semantic_checkpoint": "artifacts\\checkpoints\\semantic_final\\semantic_amazon_movies_and_tv_seed2026.pt",
      "prototype_bank": "artifacts\\prototypes\\sequence_dynamic_amazon_movies_and_tv_M128_seed2026.pt",
      "candidate_dynamic_source": "artifacts\\checkpoints\\continuous_dynamic\\semantic_conditioned_prior_enhanced_amazon_movies_and_tv_seed2026.pt::enhanced",
      "ranking_mode": "sampled",
      "eval_negatives": 100,
      "Recall@10": 0.37907711475993416,
      "Recall@20": 0.42150580696836204,
      "NDCG@10": 0.2607775628566742,
      "NDCG@20": 0.2716154158115387,
      "MRR@10": 0.22390319406986237,
      "MRR@20": 0.226936474442482,
      "tie_case_ratio": 0.46026898945401146,
      "all_equal_ratio": 0.0,
      "avg_tie_items": 13.498253459707204,
      "num_eval_users": 179784,
      "tie_policy": "worst",
      "beta_sem": 0.02,
      "beta_dyn": 0.0,
      "top_m": 16,
      "temperature": 0.05,
      "semantic_score_norm": "zscore",
      "prototype_score_norm": "zscore",
      "dynamic_score_norm": "zscore",
      "eval_elapsed_sec": 36.18244242668152,
      "eval_users_per_sec": 4968.818795588669
    },
    {
      "model": "sequence_dynamic_prototype",
      "stage": "source_val",
      "source": "amazon_movies_and_tv",
      "target": "",
      "seed": 2026,
      "semantic_checkpoint": "artifacts\\checkpoints\\semantic_final\\semantic_amazon_movies_and_tv_seed2026.pt",
      "prototype_bank": "artifacts\\prototypes\\sequence_dynamic_amazon_movies_and_tv_M128_seed2026.pt",
      "candidate_dynamic_source": "artifacts\\checkpoints\\continuous_dynamic\\semantic_conditioned_prior_enhanced_amazon_movies_and_tv_seed2026.pt::enhanced",
      "ranking_mode": "sampled",
      "eval_negatives": 100,
      "Recall@10": 0.3795944021714947,
      "Recall@20": 0.4218617897031994,
      "NDCG@10": 0.2610693573951721,
      "NDCG@20": 0.2718612253665924,
      "MRR@10": 0.22414188086986542,
      "MRR@20": 0.22715969383716583,
      "tie_case_ratio": 0.4601410581586793,
      "all_equal_ratio": 0.0,
      "avg_tie_items": 13.498804120500155,
      "num_eval_users": 179784,
      "tie_policy": "worst",
      "beta_sem": 0.02,
      "beta_dyn": 0.02,
      "top_m": 16,
      "temperature": 0.05,
      "semantic_score_norm": "zscore",
      "prototype_score_norm": "zscore",
      "dynamic_score_norm": "zscore",
      "eval_elapsed_sec": 36.05169343948364,
      "eval_users_per_sec": 4986.839253523149
    },
    {
      "model": "sequence_dynamic_prototype",
      "stage": "source_val",
      "source": "amazon_movies_and_tv",
      "target": "",
      "seed": 2026,
      "semantic_checkpoint": "artifacts\\checkpoints\\semantic_final\\semantic_amazon_movies_and_tv_seed2026.pt",
      "prototype_bank": "artifacts\\prototypes\\sequence_dynamic_amazon_movies_and_tv_M128_seed2026.pt",
      "candidate_dynamic_source": "artifacts\\checkpoints\\continuous_dynamic\\semantic_conditioned_prior_enhanced_amazon_movies_and_tv_seed2026.pt::enhanced",
      "ranking_mode": "sampled",
      "eval_negatives": 100,
      "Recall@10": 0.37978351799937704,
      "Recall@20": 0.42232901704267345,
      "NDCG@10": 0.26107868552207947,
      "NDCG@20": 0.2719496786594391,
      "MRR@10": 0.22408783435821533,
      "MRR@20": 0.22713203728199005,
      "tie_case_ratio": 0.4593512214657589,
      "all_equal_ratio": 0.0,
      "avg_tie_items": 13.492585547100965,
      "num_eval_users": 179784,
      "tie_policy": "worst",
      "beta_sem": 0.02,
      "beta_dyn": 0.05,
      "top_m": 16,
      "temperature": 0.05,
      "semantic_score_norm": "zscore",
      "prototype_score_norm": "zscore",
      "dynamic_score_norm": "zscore",
      "eval_elapsed_sec": 38.13995313644409,
      "eval_users_per_sec": 4713.797087186506
    },
    {
      "model": "sequence_dynamic_prototype",
      "stage": "source_val",
      "source": "amazon_movies_and_tv",
      "target": "",
      "seed": 2026,
      "semantic_checkpoint": "artifacts\\checkpoints\\semantic_final\\semantic_amazon_movies_and_tv_seed2026.pt",
      "prototype_bank": "artifacts\\prototypes\\sequence_dynamic_amazon_movies_and_tv_M128_seed2026.pt",
      "candidate_dynamic_source": "artifacts\\checkpoints\\continuous_dynamic\\semantic_conditioned_prior_enhanced_amazon_movies_and_tv_seed2026.pt::enhanced",
      "ranking_mode": "sampled",
      "eval_negatives": 100,
      "Recall@10": 0.37975570684821786,
      "Recall@20": 0.4227183731589018,
      "NDCG@10": 0.2608487606048584,
      "NDCG@20": 0.2718204855918884,
      "MRR@10": 0.22380207479000092,
      "MRR@20": 0.22687150537967682,
      "tie_case_ratio": 0.4593011613936724,
      "all_equal_ratio": 0.0,
      "avg_tie_items": 13.490521959684955,
      "num_eval_users": 179784,
      "tie_policy": "worst",
      "beta_sem": 0.02,
      "beta_dyn": 0.08,
      "top_m": 16,
      "temperature": 0.05,
      "semantic_score_norm": "zscore",
      "prototype_score_norm": "zscore",
      "dynamic_score_norm": "zscore",
      "eval_elapsed_sec": 59.26679730415344,
      "eval_users_per_sec": 3033.4691290531514
    },
    {
      "model": "sequence_dynamic_prototype",
      "stage": "source_val",
      "source": "amazon_movies_and_tv",
      "target": "",
      "seed": 2026,
      "semantic_checkpoint": "artifacts\\checkpoints\\semantic_final\\semantic_amazon_movies_and_tv_seed2026.pt",
      "prototype_bank": "artifacts\\prototypes\\sequence_dynamic_amazon_movies_and_tv_M128_seed2026.pt",
      "candidate_dynamic_source": "artifacts\\checkpoints\\continuous_dynamic\\semantic_conditioned_prior_enhanced_amazon_movies_and_tv_seed2026.pt::enhanced",
      "ranking_mode": "sampled",
      "eval_negatives": 100,
      "Recall@10": 0.3798280158412317,
      "Recall@20": 0.422779557691452,
      "NDCG@10": 0.26044052839279175,
      "NDCG@20": 0.271401584148407,
      "MRR@10": 0.2232532799243927,
      "MRR@20": 0.22631528973579407,
      "tie_case_ratio": 0.45942353045877277,
      "all_equal_ratio": 0.0,
      "avg_tie_items": 13.491395229831353,
      "num_eval_users": 179784,
      "tie_policy": "worst",
      "beta_sem": 0.02,
      "beta_dyn": 0.1,
      "top_m": 16,
      "temperature": 0.05,
      "semantic_score_norm": "zscore",
      "prototype_score_norm": "zscore",
      "dynamic_score_norm": "zscore",
      "eval_elapsed_sec": 59.486955642700195,
      "eval_users_per_sec": 3022.2424068874298
    },
    {
      "model": "sequence_dynamic_prototype",
      "stage": "source_val",
      "source": "amazon_movies_and_tv",
      "target": "",
      "seed": 2026,
      "semantic_checkpoint": "artifacts\\checkpoints\\semantic_final\\semantic_amazon_movies_and_tv_seed2026.pt",
      "prototype_bank": "artifacts\\prototypes\\sequence_dynamic_amazon_movies_and_tv_M128_seed2026.pt",
      "candidate_dynamic_source": "artifacts\\checkpoints\\continuous_dynamic\\semantic_conditioned_prior_enhanced_amazon_movies_and_tv_seed2026.pt::enhanced",
      "ranking_mode": "sampled",
      "eval_negatives": 100,
      "Recall@10": 0.37950540648778536,
      "Recall@20": 0.42277399546122013,
      "NDCG@10": 0.2592850625514984,
      "NDCG@20": 0.27033382654190063,
      "MRR@10": 0.22185544669628143,
      "MRR@20": 0.22494564950466156,
      "tie_case_ratio": 0.45901192542161706,
      "all_equal_ratio": 0.0,
      "avg_tie_items": 13.488908912917724,
      "num_eval_users": 179784,
      "tie_policy": "worst",
      "beta_sem": 0.02,
      "beta_dyn": 0.15,
      "top_m": 16,
      "temperature": 0.05,
      "semantic_score_norm": "zscore",
      "prototype_score_norm": "zscore",
      "dynamic_score_norm": "zscore",
      "eval_elapsed_sec": 45.338473081588745,
      "eval_users_per_sec": 3965.373948003721
    },
    {
      "model": "sequence_dynamic_prototype",
      "stage": "source_val",
      "source": "amazon_movies_and_tv",
      "target": "",
      "seed": 2026,
      "semantic_checkpoint": "artifacts\\checkpoints\\semantic_final\\semantic_amazon_movies_and_tv_seed2026.pt",
      "prototype_bank": "artifacts\\prototypes\\sequence_dynamic_amazon_movies_and_tv_M128_seed2026.pt",
      "candidate_dynamic_source": "artifacts\\checkpoints\\continuous_dynamic\\semantic_conditioned_prior_enhanced_amazon_movies_and_tv_seed2026.pt::enhanced",
      "ranking_mode": "sampled",
      "eval_negatives": 100,
      "Recall@10": 0.37868219641347395,
      "Recall@20": 0.42231789258220975,
      "NDCG@10": 0.2575439214706421,
      "NDCG@20": 0.2686883211135864,
      "MRR@10": 0.21984215080738068,
      "MRR@20": 0.22295987606048584,
      "tie_case_ratio": 0.4589006808169804,
      "all_equal_ratio": 0.0,
      "avg_tie_items": 13.491245049615094,
      "num_eval_users": 179784,
      "tie_policy": "worst",
      "beta_sem": 0.02,
      "beta_dyn": 0.2,
      "top_m": 16,
      "temperature": 0.05,
      "semantic_score_norm": "zscore",
      "prototype_score_norm": "zscore",
      "dynamic_score_norm": "zscore",
      "eval_elapsed_sec": 59.30446791648865,
      "eval_users_per_sec": 3031.5422482698636
    },
    {
      "model": "sequence_dynamic_prototype",
      "stage": "source_val",
      "source": "amazon_movies_and_tv",
      "target": "",
      "seed": 2026,
      "semantic_checkpoint": "artifacts\\checkpoints\\semantic_final\\semantic_amazon_movies_and_tv_seed2026.pt",
      "prototype_bank": "artifacts\\prototypes\\sequence_dynamic_amazon_movies_and_tv_M128_seed2026.pt",
      "candidate_dynamic_source": "artifacts\\checkpoints\\continuous_dynamic\\semantic_conditioned_prior_enhanced_amazon_movies_and_tv_seed2026.pt::enhanced",
      "ranking_mode": "sampled",
      "eval_negatives": 100,
      "Recall@10": 0.3766631068393183,
      "Recall@20": 0.41882481199661814,
      "NDCG@10": 0.259294718503952,
      "NDCG@20": 0.27006518840789795,
      "MRR@10": 0.22269371151924133,
      "MRR@20": 0.2257084846496582,
      "tie_case_ratio": 0.45944021714946826,
      "all_equal_ratio": 0.0,
      "avg_tie_items": 13.491067058247674,
      "num_eval_users": 179784,
      "tie_policy": "worst",
      "beta_sem": 0.05,
      "beta_dyn": 0.0,
      "top_m": 16,
      "temperature": 0.05,
      "semantic_score_norm": "zscore",
      "prototype_score_norm": "zscore",
      "dynamic_score_norm": "zscore",
      "eval_elapsed_sec": 59.21662664413452,
      "eval_users_per_sec": 3036.039203658485
    },
    {
      "model": "sequence_dynamic_prototype",
      "stage": "source_val",
      "source": "amazon_movies_and_tv",
      "target": "",
      "seed": 2026,
      "semantic_checkpoint": "artifacts\\checkpoints\\semantic_final\\semantic_amazon_movies_and_tv_seed2026.pt",
      "prototype_bank": "artifacts\\prototypes\\sequence_dynamic_amazon_movies_and_tv_M128_seed2026.pt",
      "candidate_dynamic_source": "artifacts\\checkpoints\\continuous_dynamic\\semantic_conditioned_prior_enhanced_amazon_movies_and_tv_seed2026.pt::enhanced",
      "ranking_mode": "sampled",
      "eval_negatives": 100,
      "Recall@10": 0.37725270324389265,
      "Recall@20": 0.4193365371779469,
      "NDCG@10": 0.2596789300441742,
      "NDCG@20": 0.2704251706600189,
      "MRR@10": 0.2230207920074463,
      "MRR@20": 0.22602654993534088,
      "tie_case_ratio": 0.45940128153784543,
      "all_equal_ratio": 0.0,
      "avg_tie_items": 13.491940328394072,
      "num_eval_users": 179784,
      "tie_policy": "worst",
      "beta_sem": 0.05,
      "beta_dyn": 0.02,
      "top_m": 16,
      "temperature": 0.05,
      "semantic_score_norm": "zscore",
      "prototype_score_norm": "zscore",
      "dynamic_score_norm": "zscore",
      "eval_elapsed_sec": 59.025094747543335,
      "eval_users_per_sec": 3045.890917565748
    },
    {
      "model": "sequence_dynamic_prototype",
      "stage": "source_val",
      "source": "amazon_movies_and_tv",
      "target": "",
      "seed": 2026,
      "semantic_checkpoint": "artifacts\\checkpoints\\semantic_final\\semantic_amazon_movies_and_tv_seed2026.pt",
      "prototype_bank": "artifacts\\prototypes\\sequence_dynamic_amazon_movies_and_tv_M128_seed2026.pt",
      "candidate_dynamic_source": "artifacts\\checkpoints\\continuous_dynamic\\semantic_conditioned_prior_enhanced_amazon_movies_and_tv_seed2026.pt::enhanced",
      "ranking_mode": "sampled",
      "eval_negatives": 100,
      "Recall@10": 0.3776031237484982,
      "Recall@20": 0.42002069149646243,
      "NDCG@10": 0.259898841381073,
      "NDCG@20": 0.2707347571849823,
      "MRR@10": 0.22320695221424103,
      "MRR@20": 0.2262403666973114,
      "tie_case_ratio": 0.4590897966448627,
      "all_equal_ratio": 0.0,
      "avg_tie_items": 13.490972500333735,
      "num_eval_users": 179784,
      "tie_policy": "worst",
      "beta_sem": 0.05,
      "beta_dyn": 0.05,
      "top_m": 16,
      "temperature": 0.05,
      "semantic_score_norm": "zscore",
      "prototype_score_norm": "zscore",
      "dynamic_score_norm": "zscore",
      "eval_elapsed_sec": 57.780290603637695,
      "eval_users_per_sec": 3111.5108304540317
    },
    {
      "model": "sequence_dynamic_prototype",
      "stage": "source_val",
      "source": "amazon_movies_and_tv",
      "target": "",
      "seed": 2026,
      "semantic_checkpoint": "artifacts\\checkpoints\\semantic_final\\semantic_amazon_movies_and_tv_seed2026.pt",
      "prototype_bank": "artifacts\\prototypes\\sequence_dynamic_amazon_movies_and_tv_M128_seed2026.pt",
      "candidate_dynamic_source": "artifacts\\checkpoints\\continuous_dynamic\\semantic_conditioned_prior_enhanced_amazon_movies_and_tv_seed2026.pt::enhanced",
      "ranking_mode": "sampled",
      "eval_negatives": 100,
      "Recall@10": 0.37774774173452585,
      "Recall@20": 0.4202988030080541,
      "NDCG@10": 0.259738564491272,
      "NDCG@20": 0.2706054449081421,
      "MRR@10": 0.22295494377613068,
      "MRR@20": 0.22599510848522186,
      "tie_case_ratio": 0.4592288524006586,
      "all_equal_ratio": 0.0,
      "avg_tie_items": 13.489954612201307,
      "num_eval_users": 179784,
      "tie_policy": "worst",
      "beta_sem": 0.05,
      "beta_dyn": 0.08,
      "top_m": 16,
      "temperature": 0.05,
      "semantic_score_norm": "zscore",
      "prototype_score_norm": "zscore",
      "dynamic_score_norm": "zscore",
      "eval_elapsed_sec": 57.605093479156494,
      "eval_users_per_sec": 3120.9740170815285
    },
    {
      "model": "sequence_dynamic_prototype",
      "stage": "source_val",
      "source": "amazon_movies_and_tv",
      "target": "",
      "seed": 2026,
      "semantic_checkpoint": "artifacts\\checkpoints\\semantic_final\\semantic_amazon_movies_and_tv_seed2026.pt",
      "prototype_bank": "artifacts\\prototypes\\sequence_dynamic_amazon_movies_and_tv_M128_seed2026.pt",
      "candidate_dynamic_source": "artifacts\\checkpoints\\continuous_dynamic\\semantic_conditioned_prior_enhanced_amazon_movies_and_tv_seed2026.pt::enhanced",
      "ranking_mode": "sampled",
      "eval_negatives": 100,
      "Recall@10": 0.37779223957638053,
      "Recall@20": 0.42046010768477726,
      "NDCG@10": 0.2594437003135681,
      "NDCG@20": 0.2703345715999603,
      "MRR@10": 0.22256417572498322,
      "MRR@20": 0.2256079465150833,
      "tie_case_ratio": 0.45918991678903576,
      "all_equal_ratio": 0.0,
      "avg_tie_items": 13.491823521559205,
      "num_eval_users": 179784,
      "tie_policy": "worst",
      "beta_sem": 0.05,
      "beta_dyn": 0.1,
      "top_m": 16,
      "temperature": 0.05,
      "semantic_score_norm": "zscore",
      "prototype_score_norm": "zscore",
      "dynamic_score_norm": "zscore",
      "eval_elapsed_sec": 57.63646078109741,
      "eval_users_per_sec": 3119.275499632385
    },
    {
      "model": "sequence_dynamic_prototype",
      "stage": "source_val",
      "source": "amazon_movies_and_tv",
      "target": "",
      "seed": 2026,
      "semantic_checkpoint": "artifacts\\checkpoints\\semantic_final\\semantic_amazon_movies_and_tv_seed2026.pt",
      "prototype_bank": "artifacts\\prototypes\\sequence_dynamic_amazon_movies_and_tv_M128_seed2026.pt",
      "candidate_dynamic_source": "artifacts\\checkpoints\\continuous_dynamic\\semantic_conditioned_prior_enhanced_amazon_movies_and_tv_seed2026.pt::enhanced",
      "ranking_mode": "sampled",
      "eval_negatives": 100,
      "Recall@10": 0.37792573310194455,
      "Recall@20": 0.42077159257776,
      "NDCG@10": 0.25845780968666077,
      "NDCG@20": 0.2693968713283539,
      "MRR@10": 0.221247598528862,
      "MRR@20": 0.22430624067783356,
      "tie_case_ratio": 0.4589396164286032,
      "all_equal_ratio": 0.0,
      "avg_tie_items": 13.493342010412494,
      "num_eval_users": 179784,
      "tie_policy": "worst",
      "beta_sem": 0.05,
      "beta_dyn": 0.15,
      "top_m": 16,
      "temperature": 0.05,
      "semantic_score_norm": "zscore",
      "prototype_score_norm": "zscore",
      "dynamic_score_norm": "zscore",
      "eval_elapsed_sec": 59.09496283531189,
      "eval_users_per_sec": 3042.2897548988894
    },
    {
      "model": "sequence_dynamic_prototype",
      "stage": "source_val",
      "source": "amazon_movies_and_tv",
      "target": "",
      "seed": 2026,
      "semantic_checkpoint": "artifacts\\checkpoints\\semantic_final\\semantic_amazon_movies_and_tv_seed2026.pt",
      "prototype_bank": "artifacts\\prototypes\\sequence_dynamic_amazon_movies_and_tv_M128_seed2026.pt",
      "candidate_dynamic_source": "artifacts\\checkpoints\\continuous_dynamic\\semantic_conditioned_prior_enhanced_amazon_movies_and_tv_seed2026.pt::enhanced",
      "ranking_mode": "sampled",
      "eval_negatives": 100,
      "Recall@10": 0.377241578783429,
      "Recall@20": 0.42050460552663194,
      "NDCG@10": 0.25680944323539734,
      "NDCG@20": 0.2678571045398712,
      "MRR@10": 0.21931259334087372,
      "MRR@20": 0.2224026322364807,
      "tie_case_ratio": 0.4591009211053264,
      "all_equal_ratio": 0.0,
      "avg_tie_items": 13.494832688114627,
      "num_eval_users": 179784,
      "tie_policy": "worst",
      "beta_sem": 0.05,
      "beta_dyn": 0.2,
      "top_m": 16,
      "temperature": 0.05,
      "semantic_score_norm": "zscore",
      "prototype_score_norm": "zscore",
      "dynamic_score_norm": "zscore",
      "eval_elapsed_sec": 54.792513608932495,
      "eval_users_per_sec": 3281.178178522018
    },
    {
      "model": "sequence_dynamic_prototype",
      "stage": "source_val",
      "source": "amazon_movies_and_tv",
      "target": "",
      "seed": 2026,
      "semantic_checkpoint": "artifacts\\checkpoints\\semantic_final\\semantic_amazon_movies_and_tv_seed2026.pt",
      "prototype_bank": "artifacts\\prototypes\\sequence_dynamic_amazon_movies_and_tv_M128_seed2026.pt",
      "candidate_dynamic_source": "artifacts\\checkpoints\\continuous_dynamic\\semantic_conditioned_prior_enhanced_amazon_movies_and_tv_seed2026.pt::enhanced",
      "ranking_mode": "sampled",
      "eval_negatives": 100,
      "Recall@10": 0.3742935967605571,
      "Recall@20": 0.4160603835713968,
      "NDCG@10": 0.2578533887863159,
      "NDCG@20": 0.2685209810733795,
      "MRR@10": 0.2215229868888855,
      "MRR@20": 0.22450782358646393,
      "tie_case_ratio": 0.45934009700529527,
      "all_equal_ratio": 0.0,
      "avg_tie_items": 13.494960619409959,
      "num_eval_users": 179784,
      "tie_policy": "worst",
      "beta_sem": 0.08,
      "beta_dyn": 0.0,
      "top_m": 16,
      "temperature": 0.05,
      "semantic_score_norm": "zscore",
      "prototype_score_norm": "zscore",
      "dynamic_score_norm": "zscore",
      "eval_elapsed_sec": 35.71184730529785,
      "eval_users_per_sec": 5034.295718813993
    },
    {
      "model": "sequence_dynamic_prototype",
      "stage": "source_val",
      "source": "amazon_movies_and_tv",
      "target": "",
      "seed": 2026,
      "semantic_checkpoint": "artifacts\\checkpoints\\semantic_final\\semantic_amazon_movies_and_tv_seed2026.pt",
      "prototype_bank": "artifacts\\prototypes\\sequence_dynamic_amazon_movies_and_tv_M128_seed2026.pt",
      "candidate_dynamic_source": "artifacts\\checkpoints\\continuous_dynamic\\semantic_conditioned_prior_enhanced_amazon_movies_and_tv_seed2026.pt::enhanced",
      "ranking_mode": "sampled",
      "eval_negatives": 100,
      "Recall@10": 0.3750166866906955,
      "Recall@20": 0.416822409113158,
      "NDCG@10": 0.25826549530029297,
      "NDCG@20": 0.26893988251686096,
      "MRR@10": 0.2218455970287323,
      "MRR@20": 0.224830761551857,
      "tie_case_ratio": 0.4592566635518177,
      "all_equal_ratio": 0.0,
      "avg_tie_items": 13.495544653584302,
      "num_eval_users": 179784,
      "tie_policy": "worst",
      "beta_sem": 0.08,
      "beta_dyn": 0.02,
      "top_m": 16,
      "temperature": 0.05,
      "semantic_score_norm": "zscore",
      "prototype_score_norm": "zscore",
      "dynamic_score_norm": "zscore",
      "eval_elapsed_sec": 33.87843608856201,
      "eval_users_per_sec": 5306.738467207417
    },
    {
      "model": "sequence_dynamic_prototype",
      "stage": "source_val",
      "source": "amazon_movies_and_tv",
      "target": "",
      "seed": 2026,
      "semantic_checkpoint": "artifacts\\checkpoints\\semantic_final\\semantic_amazon_movies_and_tv_seed2026.pt",
      "prototype_bank": "artifacts\\prototypes\\sequence_dynamic_amazon_movies_and_tv_M128_seed2026.pt",
      "candidate_dynamic_source": "artifacts\\checkpoints\\continuous_dynamic\\semantic_conditioned_prior_enhanced_amazon_movies_and_tv_seed2026.pt::enhanced",
      "ranking_mode": "sampled",
      "eval_negatives": 100,
      "Recall@10": 0.3754394161883149,
      "Recall@20": 0.4176956792595559,
      "NDCG@10": 0.2584921419620514,
      "NDCG@20": 0.2692824602127075,
      "MRR@10": 0.22201919555664062,
      "MRR@20": 0.22503750026226044,
      "tie_case_ratio": 0.4591064833355582,
      "all_equal_ratio": 0.0,
      "avg_tie_items": 13.491489787745294,
      "num_eval_users": 179784,
      "tie_policy": "worst",
      "beta_sem": 0.08,
      "beta_dyn": 0.05,
      "top_m": 16,
      "temperature": 0.05,
      "semantic_score_norm": "zscore",
      "prototype_score_norm": "zscore",
      "dynamic_score_norm": "zscore",
      "eval_elapsed_sec": 36.32483434677124,
      "eval_users_per_sec": 4949.3412215926655
    },
    {
      "model": "sequence_dynamic_prototype",
      "stage": "source_val",
      "source": "amazon_movies_and_tv",
      "target": "",
      "seed": 2026,
      "semantic_checkpoint": "artifacts\\checkpoints\\semantic_final\\semantic_amazon_movies_and_tv_seed2026.pt",
      "prototype_bank": "artifacts\\prototypes\\sequence_dynamic_amazon_movies_and_tv_M128_seed2026.pt",
      "candidate_dynamic_source": "artifacts\\checkpoints\\continuous_dynamic\\semantic_conditioned_prior_enhanced_amazon_movies_and_tv_seed2026.pt::enhanced",
      "ranking_mode": "sampled",
      "eval_negatives": 100,
      "Recall@10": 0.3756897165487474,
      "Recall@20": 0.4180572242246251,
      "NDCG@10": 0.258424311876297,
      "NDCG@20": 0.26924771070480347,
      "MRR@10": 0.2218570113182068,
      "MRR@20": 0.22488687932491302,
      "tie_case_ratio": 0.4591009211053264,
      "all_equal_ratio": 0.0,
      "avg_tie_items": 13.489515196012993,
      "num_eval_users": 179784,
      "tie_policy": "worst",
      "beta_sem": 0.08,
      "beta_dyn": 0.08,
      "top_m": 16,
      "temperature": 0.05,
      "semantic_score_norm": "zscore",
      "prototype_score_norm": "zscore",
      "dynamic_score_norm": "zscore",
      "eval_elapsed_sec": 36.525675773620605,
      "eval_users_per_sec": 4922.126591558991
    },
    {
      "model": "sequence_dynamic_prototype",
      "stage": "source_val",
      "source": "amazon_movies_and_tv",
      "target": "",
      "seed": 2026,
      "semantic_checkpoint": "artifacts\\checkpoints\\semantic_final\\semantic_amazon_movies_and_tv_seed2026.pt",
      "prototype_bank": "artifacts\\prototypes\\sequence_dynamic_amazon_movies_and_tv_M128_seed2026.pt",
      "candidate_dynamic_source": "artifacts\\checkpoints\\continuous_dynamic\\semantic_conditioned_prior_enhanced_amazon_movies_and_tv_seed2026.pt::enhanced",
      "ranking_mode": "sampled",
      "eval_negatives": 100,
      "Recall@10": 0.3759900769812664,
      "Recall@20": 0.41834089796644863,
      "NDCG@10": 0.25836849212646484,
      "NDCG@20": 0.26917651295661926,
      "MRR@10": 0.22169619798660278,
      "MRR@20": 0.2247157245874405,
      "tie_case_ratio": 0.4590063631913852,
      "all_equal_ratio": 0.0,
      "avg_tie_items": 13.492630044942821,
      "num_eval_users": 179784,
      "tie_policy": "worst",
      "beta_sem": 0.08,
      "beta_dyn": 0.1,
      "top_m": 16,
      "temperature": 0.05,
      "semantic_score_norm": "zscore",
      "prototype_score_norm": "zscore",
      "dynamic_score_norm": "zscore",
      "eval_elapsed_sec": 36.48819184303284,
      "eval_users_per_sec": 4927.183039746281
    },
    {
      "model": "sequence_dynamic_prototype",
      "stage": "source_val",
      "source": "amazon_movies_and_tv",
      "target": "",
      "seed": 2026,
      "semantic_checkpoint": "artifacts\\checkpoints\\semantic_final\\semantic_amazon_movies_and_tv_seed2026.pt",
      "prototype_bank": "artifacts\\prototypes\\sequence_dynamic_amazon_movies_and_tv_M128_seed2026.pt",
      "candidate_dynamic_source": "artifacts\\checkpoints\\continuous_dynamic\\semantic_conditioned_prior_enhanced_amazon_movies_and_tv_seed2026.pt::enhanced",
      "ranking_mode": "sampled",
      "eval_negatives": 100,
      "Recall@10": 0.37606238597428027,
      "Recall@20": 0.4187691896942998,
      "NDCG@10": 0.2574141025543213,
      "NDCG@20": 0.2683160603046417,
      "MRR@10": 0.22043737769126892,
      "MRR@20": 0.2234847992658615,
      "tie_case_ratio": 0.45886174520535755,
      "all_equal_ratio": 0.0,
      "avg_tie_items": 13.493058336670671,
      "num_eval_users": 179784,
      "tie_policy": "worst",
      "beta_sem": 0.08,
      "beta_dyn": 0.15,
      "top_m": 16,
      "temperature": 0.05,
      "semantic_score_norm": "zscore",
      "prototype_score_norm": "zscore",
      "dynamic_score_norm": "zscore",
      "eval_elapsed_sec": 36.45884847640991,
      "eval_users_per_sec": 4931.148610366184
    },
    {
      "model": "sequence_dynamic_prototype",
      "stage": "source_val",
      "source": "amazon_movies_and_tv",
      "target": "",
      "seed": 2026,
      "semantic_checkpoint": "artifacts\\checkpoints\\semantic_final\\semantic_amazon_movies_and_tv_seed2026.pt",
      "prototype_bank": "artifacts\\prototypes\\sequence_dynamic_amazon_movies_and_tv_M128_seed2026.pt",
      "candidate_dynamic_source": "artifacts\\checkpoints\\continuous_dynamic\\semantic_conditioned_prior_enhanced_amazon_movies_and_tv_seed2026.pt::enhanced",
      "ranking_mode": "sampled",
      "eval_negatives": 100,
      "Recall@10": 0.3755784719441107,
      "Recall@20": 0.41854113825479466,
      "NDCG@10": 0.2560102045536041,
      "NDCG@20": 0.2669774889945984,
      "MRR@10": 0.21876850724220276,
      "MRR@20": 0.22183407843112946,
      "tie_case_ratio": 0.45897298980999424,
      "all_equal_ratio": 0.0,
      "avg_tie_items": 13.49636230142838,
      "num_eval_users": 179784,
      "tie_policy": "worst",
      "beta_sem": 0.08,
      "beta_dyn": 0.2,
      "top_m": 16,
      "temperature": 0.05,
      "semantic_score_norm": "zscore",
      "prototype_score_norm": "zscore",
      "dynamic_score_norm": "zscore",
      "eval_elapsed_sec": 36.45882987976074,
      "eval_users_per_sec": 4931.151125609844
    },
    {
      "model": "sequence_dynamic_prototype",
      "stage": "source_val",
      "source": "amazon_movies_and_tv",
      "target": "",
      "seed": 2026,
      "semantic_checkpoint": "artifacts\\checkpoints\\semantic_final\\semantic_amazon_movies_and_tv_seed2026.pt",
      "prototype_bank": "artifacts\\prototypes\\sequence_dynamic_amazon_movies_and_tv_M128_seed2026.pt",
      "candidate_dynamic_source": "artifacts\\checkpoints\\continuous_dynamic\\semantic_conditioned_prior_enhanced_amazon_movies_and_tv_seed2026.pt::enhanced",
      "ranking_mode": "sampled",
      "eval_negatives": 100,
      "Recall@10": 0.3728752280514395,
      "Recall@20": 0.4145085213367152,
      "NDCG@10": 0.2568678557872772,
      "NDCG@20": 0.26749885082244873,
      "MRR@10": 0.22065900266170502,
      "MRR@20": 0.22363215684890747,
      "tie_case_ratio": 0.45941240599830907,
      "all_equal_ratio": 0.0,
      "avg_tie_items": 13.49390379566591,
      "num_eval_users": 179784,
      "tie_policy": "worst",
      "beta_sem": 0.1,
      "beta_dyn": 0.0,
      "top_m": 16,
      "temperature": 0.05,
      "semantic_score_norm": "zscore",
      "prototype_score_norm": "zscore",
      "dynamic_score_norm": "zscore",
      "eval_elapsed_sec": 36.43913245201111,
      "eval_users_per_sec": 4933.816693818614
    },
    {
      "model": "sequence_dynamic_prototype",
      "stage": "source_val",
      "source": "amazon_movies_and_tv",
      "target": "",
      "seed": 2026,
      "semantic_checkpoint": "artifacts\\checkpoints\\semantic_final\\semantic_amazon_movies_and_tv_seed2026.pt",
      "prototype_bank": "artifacts\\prototypes\\sequence_dynamic_amazon_movies_and_tv_M128_seed2026.pt",
      "candidate_dynamic_source": "artifacts\\checkpoints\\continuous_dynamic\\semantic_conditioned_prior_enhanced_amazon_movies_and_tv_seed2026.pt::enhanced",
      "ranking_mode": "sampled",
      "eval_negatives": 100,
      "Recall@10": 0.3733647043118409,
      "Recall@20": 0.41519823788546256,
      "NDCG@10": 0.2571703791618347,
      "NDCG@20": 0.26784899830818176,
      "MRR@10": 0.22090966999530792,
      "MRR@20": 0.22389458119869232,
      "tie_case_ratio": 0.4593345347750634,
      "all_equal_ratio": 0.0,
      "avg_tie_items": 13.496223245672585,
      "num_eval_users": 179784,
      "tie_policy": "worst",
      "beta_sem": 0.1,
      "beta_dyn": 0.02,
      "top_m": 16,
      "temperature": 0.05,
      "semantic_score_norm": "zscore",
      "prototype_score_norm": "zscore",
      "dynamic_score_norm": "zscore",
      "eval_elapsed_sec": 36.406381130218506,
      "eval_users_per_sec": 4938.255174469217
    },
    {
      "model": "sequence_dynamic_prototype",
      "stage": "source_val",
      "source": "amazon_movies_and_tv",
      "target": "",
      "seed": 2026,
      "semantic_checkpoint": "artifacts\\checkpoints\\semantic_final\\semantic_amazon_movies_and_tv_seed2026.pt",
      "prototype_bank": "artifacts\\prototypes\\sequence_dynamic_amazon_movies_and_tv_M128_seed2026.pt",
      "candidate_dynamic_source": "artifacts\\checkpoints\\continuous_dynamic\\semantic_conditioned_prior_enhanced_amazon_movies_and_tv_seed2026.pt::enhanced",
      "ranking_mode": "sampled",
      "eval_negatives": 100,
      "Recall@10": 0.37408779424197924,
      "Recall@20": 0.4160993191830196,
      "NDCG@10": 0.25761792063713074,
      "NDCG@20": 0.26834380626678467,
      "MRR@10": 0.2212827503681183,
      "MRR@20": 0.22428198158740997,
      "tie_case_ratio": 0.4592288524006586,
      "all_equal_ratio": 0.0,
      "avg_tie_items": 13.492674542784675,
      "num_eval_users": 179784,
      "tie_policy": "worst",
      "beta_sem": 0.1,
      "beta_dyn": 0.05,
      "top_m": 16,
      "temperature": 0.05,
      "semantic_score_norm": "zscore",
      "prototype_score_norm": "zscore",
      "dynamic_score_norm": "zscore",
      "eval_elapsed_sec": 36.527456283569336,
      "eval_users_per_sec": 4921.886665315643
    },
    {
      "model": "sequence_dynamic_prototype",
      "stage": "source_val",
      "source": "amazon_movies_and_tv",
      "target": "",
      "seed": 2026,
      "semantic_checkpoint": "artifacts\\checkpoints\\semantic_final\\semantic_amazon_movies_and_tv_seed2026.pt",
      "prototype_bank": "artifacts\\prototypes\\sequence_dynamic_amazon_movies_and_tv_M128_seed2026.pt",
      "candidate_dynamic_source": "artifacts\\checkpoints\\continuous_dynamic\\semantic_conditioned_prior_enhanced_amazon_movies_and_tv_seed2026.pt::enhanced",
      "ranking_mode": "sampled",
      "eval_negatives": 100,
      "Recall@10": 0.3745438971209896,
      "Recall@20": 0.41672785119921685,
      "NDCG@10": 0.2576744854450226,
      "NDCG@20": 0.2684433162212372,
      "MRR@10": 0.22122013568878174,
      "MRR@20": 0.2242307811975479,
      "tie_case_ratio": 0.4592121657099631,
      "all_equal_ratio": 0.0,
      "avg_tie_items": 13.492040448538246,
      "num_eval_users": 179784,
      "tie_policy": "worst",
      "beta_sem": 0.1,
      "beta_dyn": 0.08,
      "top_m": 16,
      "temperature": 0.05,
      "semantic_score_norm": "zscore",
      "prototype_score_norm": "zscore",
      "dynamic_score_norm": "zscore",
      "eval_elapsed_sec": 36.49470663070679,
      "eval_users_per_sec": 4926.303472425479
    },
    {
      "model": "sequence_dynamic_prototype",
      "stage": "source_val",
      "source": "amazon_movies_and_tv",
      "target": "",
      "seed": 2026,
      "semantic_checkpoint": "artifacts\\checkpoints\\semantic_final\\semantic_amazon_movies_and_tv_seed2026.pt",
      "prototype_bank": "artifacts\\prototypes\\sequence_dynamic_amazon_movies_and_tv_M128_seed2026.pt",
      "candidate_dynamic_source": "artifacts\\checkpoints\\continuous_dynamic\\semantic_conditioned_prior_enhanced_amazon_movies_and_tv_seed2026.pt::enhanced",
      "ranking_mode": "sampled",
      "eval_negatives": 100,
      "Recall@10": 0.37461064388377163,
      "Recall@20": 0.4168724691852445,
      "NDCG@10": 0.25753065943717957,
      "NDCG@20": 0.26831522583961487,
      "MRR@10": 0.2210148423910141,
      "MRR@20": 0.22402752935886383,
      "tie_case_ratio": 0.4590174876518489,
      "all_equal_ratio": 0.0,
      "avg_tie_items": 13.494949494949495,
      "num_eval_users": 179784,
      "tie_policy": "worst",
      "beta_sem": 0.1,
      "beta_dyn": 0.1,
      "top_m": 16,
      "temperature": 0.05,
      "semantic_score_norm": "zscore",
      "prototype_score_norm": "zscore",
      "dynamic_score_norm": "zscore",
      "eval_elapsed_sec": 36.51734137535095,
      "eval_users_per_sec": 4923.249974636801
    },
    {
      "model": "sequence_dynamic_prototype",
      "stage": "source_val",
      "source": "amazon_movies_and_tv",
      "target": "",
      "seed": 2026,
      "semantic_checkpoint": "artifacts\\checkpoints\\semantic_final\\semantic_amazon_movies_and_tv_seed2026.pt",
      "prototype_bank": "artifacts\\prototypes\\sequence_dynamic_amazon_movies_and_tv_M128_seed2026.pt",
      "candidate_dynamic_source": "artifacts\\checkpoints\\continuous_dynamic\\semantic_conditioned_prior_enhanced_amazon_movies_and_tv_seed2026.pt::enhanced",
      "ranking_mode": "sampled",
      "eval_negatives": 100,
      "Recall@10": 0.3747218884884083,
      "Recall@20": 0.4172840742224002,
      "NDCG@10": 0.2567214369773865,
      "NDCG@20": 0.2675788104534149,
      "MRR@10": 0.21993477642536163,
      "MRR@20": 0.22296568751335144,
      "tie_case_ratio": 0.45878387398211185,
      "all_equal_ratio": 0.0,
      "avg_tie_items": 13.49799759711654,
      "num_eval_users": 179784,
      "tie_policy": "worst",
      "beta_sem": 0.1,
      "beta_dyn": 0.15,
      "top_m": 16,
      "temperature": 0.05,
      "semantic_score_norm": "zscore",
      "prototype_score_norm": "zscore",
      "dynamic_score_norm": "zscore",
      "eval_elapsed_sec": 36.48207712173462,
      "eval_users_per_sec": 4928.008879540787
    },
    {
      "model": "sequence_dynamic_prototype",
      "stage": "source_val",
      "source": "amazon_movies_and_tv",
      "target": "",
      "seed": 2026,
      "semantic_checkpoint": "artifacts\\checkpoints\\semantic_final\\semantic_amazon_movies_and_tv_seed2026.pt",
      "prototype_bank": "artifacts\\prototypes\\sequence_dynamic_amazon_movies_and_tv_M128_seed2026.pt",
      "candidate_dynamic_source": "artifacts\\checkpoints\\continuous_dynamic\\semantic_conditioned_prior_enhanced_amazon_movies_and_tv_seed2026.pt::enhanced",
      "ranking_mode": "sampled",
      "eval_negatives": 100,
      "Recall@10": 0.37419903884661593,
      "Recall@20": 0.41715614292706804,
      "NDCG@10": 0.2553499639034271,
      "NDCG@20": 0.2663148045539856,
      "MRR@10": 0.2183140218257904,
      "MRR@20": 0.22137850522994995,
      "tie_case_ratio": 0.45894517865883505,
      "all_equal_ratio": 0.0,
      "avg_tie_items": 13.503887998932052,
      "num_eval_users": 179784,
      "tie_policy": "worst",
      "beta_sem": 0.1,
      "beta_dyn": 0.2,
      "top_m": 16,
      "temperature": 0.05,
      "semantic_score_norm": "zscore",
      "prototype_score_norm": "zscore",
      "dynamic_score_norm": "zscore",
      "eval_elapsed_sec": 36.45076370239258,
      "eval_users_per_sec": 4932.242338401245
    },
    {
      "model": "sequence_dynamic_prototype",
      "stage": "source_val",
      "source": "amazon_movies_and_tv",
      "target": "",
      "seed": 2026,
      "semantic_checkpoint": "artifacts\\checkpoints\\semantic_final\\semantic_amazon_movies_and_tv_seed2026.pt",
      "prototype_bank": "artifacts\\prototypes\\sequence_dynamic_amazon_movies_and_tv_M128_seed2026.pt",
      "candidate_dynamic_source": "artifacts\\checkpoints\\continuous_dynamic\\semantic_conditioned_prior_enhanced_amazon_movies_and_tv_seed2026.pt::enhanced",
      "ranking_mode": "sampled",
      "eval_negatives": 100,
      "Recall@10": 0.3685867485426957,
      "Recall@20": 0.40984181017220667,
      "NDCG@10": 0.2538908123970032,
      "NDCG@20": 0.2644246220588684,
      "MRR@10": 0.2180681973695755,
      "MRR@20": 0.22101391851902008,
      "tie_case_ratio": 0.4595959595959596,
      "all_equal_ratio": 0.0,
      "avg_tie_items": 13.50011680683487,
      "num_eval_users": 179784,
      "tie_policy": "worst",
      "beta_sem": 0.15,
      "beta_dyn": 0.0,
      "top_m": 16,
      "temperature": 0.05,
      "semantic_score_norm": "zscore",
      "prototype_score_norm": "zscore",
      "dynamic_score_norm": "zscore",
      "eval_elapsed_sec": 36.38022184371948,
      "eval_users_per_sec": 4941.8060387951455
    },
    {
      "model": "sequence_dynamic_prototype",
      "stage": "source_val",
      "source": "amazon_movies_and_tv",
      "target": "",
      "seed": 2026,
      "semantic_checkpoint": "artifacts\\checkpoints\\semantic_final\\semantic_amazon_movies_and_tv_seed2026.pt",
      "prototype_bank": "artifacts\\prototypes\\sequence_dynamic_amazon_movies_and_tv_M128_seed2026.pt",
      "candidate_dynamic_source": "artifacts\\checkpoints\\continuous_dynamic\\semantic_conditioned_prior_enhanced_amazon_movies_and_tv_seed2026.pt::enhanced",
      "ranking_mode": "sampled",
      "eval_negatives": 100,
      "Recall@10": 0.36954345214257106,
      "Recall@20": 0.4109931918301962,
      "NDCG@10": 0.25451216101646423,
      "NDCG@20": 0.2650855481624603,
      "MRR@10": 0.218584805727005,
      "MRR@20": 0.22153636813163757,
      "tie_case_ratio": 0.4594624660703956,
      "all_equal_ratio": 0.0,
      "avg_tie_items": 13.498804120500155,
      "num_eval_users": 179784,
      "tie_policy": "worst",
      "beta_sem": 0.15,
      "beta_dyn": 0.02,
      "top_m": 16,
      "temperature": 0.05,
      "semantic_score_norm": "zscore",
      "prototype_score_norm": "zscore",
      "dynamic_score_norm": "zscore",
      "eval_elapsed_sec": 36.45618772506714,
      "eval_users_per_sec": 4931.508509771613
    },
    {
      "model": "sequence_dynamic_prototype",
      "stage": "source_val",
      "source": "amazon_movies_and_tv",
      "target": "",
      "seed": 2026,
      "semantic_checkpoint": "artifacts\\checkpoints\\semantic_final\\semantic_amazon_movies_and_tv_seed2026.pt",
      "prototype_bank": "artifacts\\prototypes\\sequence_dynamic_amazon_movies_and_tv_M128_seed2026.pt",
      "candidate_dynamic_source": "artifacts\\checkpoints\\continuous_dynamic\\semantic_conditioned_prior_enhanced_amazon_movies_and_tv_seed2026.pt::enhanced",
      "ranking_mode": "sampled",
      "eval_negatives": 100,
      "Recall@10": 0.3706225248075468,
      "Recall@20": 0.41195545766030345,
      "NDCG@10": 0.2551586329936981,
      "NDCG@20": 0.26569968461990356,
      "MRR@10": 0.21911519765853882,
      "MRR@20": 0.22205647826194763,
      "tie_case_ratio": 0.45931784808436793,
      "all_equal_ratio": 0.0,
      "avg_tie_items": 13.500233613669737,
      "num_eval_users": 179784,
      "tie_policy": "worst",
      "beta_sem": 0.15,
      "beta_dyn": 0.05,
      "top_m": 16,
      "temperature": 0.05,
      "semantic_score_norm": "zscore",
      "prototype_score_norm": "zscore",
      "dynamic_score_norm": "zscore",
      "eval_elapsed_sec": 36.373085737228394,
      "eval_users_per_sec": 4942.775581341134
    },
    {
      "model": "sequence_dynamic_prototype",
      "stage": "source_val",
      "source": "amazon_movies_and_tv",
      "target": "",
      "seed": 2026,
      "semantic_checkpoint": "artifacts\\checkpoints\\semantic_final\\semantic_amazon_movies_and_tv_seed2026.pt",
      "prototype_bank": "artifacts\\prototypes\\sequence_dynamic_amazon_movies_and_tv_M128_seed2026.pt",
      "candidate_dynamic_source": "artifacts\\checkpoints\\continuous_dynamic\\semantic_conditioned_prior_enhanced_amazon_movies_and_tv_seed2026.pt::enhanced",
      "ranking_mode": "sampled",
      "eval_negatives": 100,
      "Recall@10": 0.37107306545632535,
      "Recall@20": 0.41254505406487785,
      "NDCG@10": 0.2553286552429199,
      "NDCG@20": 0.26589804887771606,
      "MRR@10": 0.21920745074748993,
      "MRR@20": 0.22215299308300018,
      "tie_case_ratio": 0.4592121657099631,
      "all_equal_ratio": 0.0,
      "avg_tie_items": 13.508165353980331,
      "num_eval_users": 179784,
      "tie_policy": "worst",
      "beta_sem": 0.15,
      "beta_dyn": 0.08,
      "top_m": 16,
      "temperature": 0.05,
      "semantic_score_norm": "zscore",
      "prototype_score_norm": "zscore",
      "dynamic_score_norm": "zscore",
      "eval_elapsed_sec": 36.40965390205383,
      "eval_users_per_sec": 4937.81128718333
    },
    {
      "model": "sequence_dynamic_prototype",
      "stage": "source_val",
      "source": "amazon_movies_and_tv",
      "target": "",
      "seed": 2026,
      "semantic_checkpoint": "artifacts\\checkpoints\\semantic_final\\semantic_amazon_movies_and_tv_seed2026.pt",
      "prototype_bank": "artifacts\\prototypes\\sequence_dynamic_amazon_movies_and_tv_M128_seed2026.pt",
      "candidate_dynamic_source": "artifacts\\checkpoints\\continuous_dynamic\\semantic_conditioned_prior_enhanced_amazon_movies_and_tv_seed2026.pt::enhanced",
      "ranking_mode": "sampled",
      "eval_negatives": 100,
      "Recall@10": 0.37113424998887556,
      "Recall@20": 0.41287322564855605,
      "NDCG@10": 0.25529760122299194,
      "NDCG@20": 0.26593902707099915,
      "MRR@10": 0.21914507448673248,
      "MRR@20": 0.22211280465126038,
      "tie_case_ratio": 0.4591565434076447,
      "all_equal_ratio": 0.0,
      "avg_tie_items": 13.508932941752326,
      "num_eval_users": 179784,
      "tie_policy": "worst",
      "beta_sem": 0.15,
      "beta_dyn": 0.1,
      "top_m": 16,
      "temperature": 0.05,
      "semantic_score_norm": "zscore",
      "prototype_score_norm": "zscore",
      "dynamic_score_norm": "zscore",
      "eval_elapsed_sec": 36.38601851463318,
      "eval_users_per_sec": 4941.018757732374
    },
    {
      "model": "sequence_dynamic_prototype",
      "stage": "source_val",
      "source": "amazon_movies_and_tv",
      "target": "",
      "seed": 2026,
      "semantic_checkpoint": "artifacts\\checkpoints\\semantic_final\\semantic_amazon_movies_and_tv_seed2026.pt",
      "prototype_bank": "artifacts\\prototypes\\sequence_dynamic_amazon_movies_and_tv_M128_seed2026.pt",
      "candidate_dynamic_source": "artifacts\\checkpoints\\continuous_dynamic\\semantic_conditioned_prior_enhanced_amazon_movies_and_tv_seed2026.pt::enhanced",
      "ranking_mode": "sampled",
      "eval_negatives": 100,
      "Recall@10": 0.3712788679749032,
      "Recall@20": 0.4132292083833934,
      "NDCG@10": 0.2546108365058899,
      "NDCG@20": 0.2652978003025055,
      "MRR@10": 0.21821139752864838,
      "MRR@20": 0.2211872786283493,
      "tie_case_ratio": 0.45944021714946826,
      "all_equal_ratio": 0.0,
      "avg_tie_items": 13.513488408312197,
      "num_eval_users": 179784,
      "tie_policy": "worst",
      "beta_sem": 0.15,
      "beta_dyn": 0.15,
      "top_m": 16,
      "temperature": 0.05,
      "semantic_score_norm": "zscore",
      "prototype_score_norm": "zscore",
      "dynamic_score_norm": "zscore",
      "eval_elapsed_sec": 36.508174657821655,
      "eval_users_per_sec": 4924.48613728439
    },
    {
      "model": "sequence_dynamic_prototype",
      "stage": "source_val",
      "source": "amazon_movies_and_tv",
      "target": "",
      "seed": 2026,
      "semantic_checkpoint": "artifacts\\checkpoints\\semantic_final\\semantic_amazon_movies_and_tv_seed2026.pt",
      "prototype_bank": "artifacts\\prototypes\\sequence_dynamic_amazon_movies_and_tv_M128_seed2026.pt",
      "candidate_dynamic_source": "artifacts\\checkpoints\\continuous_dynamic\\semantic_conditioned_prior_enhanced_amazon_movies_and_tv_seed2026.pt::enhanced",
      "ranking_mode": "sampled",
      "eval_negatives": 100,
      "Recall@10": 0.37098406977261605,
      "Recall@20": 0.4134183242112758,
      "NDCG@10": 0.25351443886756897,
      "NDCG@20": 0.2643283009529114,
      "MRR@10": 0.21687902510166168,
      "MRR@20": 0.21989226341247559,
      "tie_case_ratio": 0.45889511858674853,
      "all_equal_ratio": 0.0,
      "avg_tie_items": 13.514673163351578,
      "num_eval_users": 179784,
      "tie_policy": "worst",
      "beta_sem": 0.15,
      "beta_dyn": 0.2,
      "top_m": 16,
      "temperature": 0.05,
      "semantic_score_norm": "zscore",
      "prototype_score_norm": "zscore",
      "dynamic_score_norm": "zscore",
      "eval_elapsed_sec": 36.35842299461365,
      "eval_users_per_sec": 4944.768919890565
    },
    {
      "model": "sequence_dynamic_prototype",
      "stage": "source_val",
      "source": "amazon_movies_and_tv",
      "target": "",
      "seed": 2026,
      "semantic_checkpoint": "artifacts\\checkpoints\\semantic_final\\semantic_amazon_movies_and_tv_seed2026.pt",
      "prototype_bank": "artifacts\\prototypes\\sequence_dynamic_amazon_movies_and_tv_M128_seed2026.pt",
      "candidate_dynamic_source": "artifacts\\checkpoints\\continuous_dynamic\\semantic_conditioned_prior_enhanced_amazon_movies_and_tv_seed2026.pt::enhanced",
      "ranking_mode": "sampled",
      "eval_negatives": 100,
      "Recall@10": 0.36428158234325636,
      "Recall@20": 0.4052307213100165,
      "NDCG@10": 0.25091037154197693,
      "NDCG@20": 0.26134565472602844,
      "MRR@10": 0.21548579633235931,
      "MRR@20": 0.21839341521263123,
      "tie_case_ratio": 0.45934565923552706,
      "all_equal_ratio": 0.0,
      "avg_tie_items": 13.513382725937792,
      "num_eval_users": 179784,
      "tie_policy": "worst",
      "beta_sem": 0.2,
      "beta_dyn": 0.0,
      "top_m": 16,
      "temperature": 0.05,
      "semantic_score_norm": "zscore",
      "prototype_score_norm": "zscore",
      "dynamic_score_norm": "zscore",
      "eval_elapsed_sec": 36.35721206665039,
      "eval_users_per_sec": 4944.933612357797
    },
    {
      "model": "sequence_dynamic_prototype",
      "stage": "source_val",
      "source": "amazon_movies_and_tv",
      "target": "",
      "seed": 2026,
      "semantic_checkpoint": "artifacts\\checkpoints\\semantic_final\\semantic_amazon_movies_and_tv_seed2026.pt",
      "prototype_bank": "artifacts\\prototypes\\sequence_dynamic_amazon_movies_and_tv_M128_seed2026.pt",
      "candidate_dynamic_source": "artifacts\\checkpoints\\continuous_dynamic\\semantic_conditioned_prior_enhanced_amazon_movies_and_tv_seed2026.pt::enhanced",
      "ranking_mode": "sampled",
      "eval_negatives": 100,
      "Recall@10": 0.3651437280291906,
      "Recall@20": 0.4061373648378054,
      "NDCG@10": 0.25149768590927124,
      "NDCG@20": 0.2619447708129883,
      "MRR@10": 0.2159883975982666,
      "MRR@20": 0.21889959275722504,
      "tie_case_ratio": 0.45917879232857206,
      "all_equal_ratio": 0.0,
      "avg_tie_items": 13.512620700396031,
      "num_eval_users": 179784,
      "tie_policy": "worst",
      "beta_sem": 0.2,
      "beta_dyn": 0.02,
      "top_m": 16,
      "temperature": 0.05,
      "semantic_score_norm": "zscore",
      "prototype_score_norm": "zscore",
      "dynamic_score_norm": "zscore",
      "eval_elapsed_sec": 36.44288372993469,
      "eval_users_per_sec": 4933.308827378085
    },
    {
      "model": "sequence_dynamic_prototype",
      "stage": "source_val",
      "source": "amazon_movies_and_tv",
      "target": "",
      "seed": 2026,
      "semantic_checkpoint": "artifacts\\checkpoints\\semantic_final\\semantic_amazon_movies_and_tv_seed2026.pt",
      "prototype_bank": "artifacts\\prototypes\\sequence_dynamic_amazon_movies_and_tv_M128_seed2026.pt",
      "candidate_dynamic_source": "artifacts\\checkpoints\\continuous_dynamic\\semantic_conditioned_prior_enhanced_amazon_movies_and_tv_seed2026.pt::enhanced",
      "ranking_mode": "sampled",
      "eval_negatives": 100,
      "Recall@10": 0.3663841053708895,
      "Recall@20": 0.4074778623236773,
      "NDCG@10": 0.25232720375061035,
      "NDCG@20": 0.26280081272125244,
      "MRR@10": 0.2166959047317505,
      "MRR@20": 0.21961505711078644,
      "tie_case_ratio": 0.4591565434076447,
      "all_equal_ratio": 0.0,
      "avg_tie_items": 13.514128064788858,
      "num_eval_users": 179784,
      "tie_policy": "worst",
      "beta_sem": 0.2,
      "beta_dyn": 0.05,
      "top_m": 16,
      "temperature": 0.05,
      "semantic_score_norm": "zscore",
      "prototype_score_norm": "zscore",
      "dynamic_score_norm": "zscore",
      "eval_elapsed_sec": 36.43819308280945,
      "eval_users_per_sec": 4933.943886608835
    },
    {
      "model": "sequence_dynamic_prototype",
      "stage": "source_val",
      "source": "amazon_movies_and_tv",
      "target": "",
      "seed": 2026,
      "semantic_checkpoint": "artifacts\\checkpoints\\semantic_final\\semantic_amazon_movies_and_tv_seed2026.pt",
      "prototype_bank": "artifacts\\prototypes\\sequence_dynamic_amazon_movies_and_tv_M128_seed2026.pt",
      "candidate_dynamic_source": "artifacts\\checkpoints\\continuous_dynamic\\semantic_conditioned_prior_enhanced_amazon_movies_and_tv_seed2026.pt::enhanced",
      "ranking_mode": "sampled",
      "eval_negatives": 100,
      "Recall@10": 0.3670404485382459,
      "Recall@20": 0.4081842655631202,
      "NDCG@10": 0.2527181804180145,
      "NDCG@20": 0.2632002532482147,
      "MRR@10": 0.21701490879058838,
      "MRR@20": 0.21993392705917358,
      "tie_case_ratio": 0.4588895563565167,
      "all_equal_ratio": 0.0,
      "avg_tie_items": 13.516052596449072,
      "num_eval_users": 179784,
      "tie_policy": "worst",
      "beta_sem": 0.2,
      "beta_dyn": 0.08,
      "top_m": 16,
      "temperature": 0.05,
      "semantic_score_norm": "zscore",
      "prototype_score_norm": "zscore",
      "dynamic_score_norm": "zscore",
      "eval_elapsed_sec": 36.42827820777893,
      "eval_users_per_sec": 4935.286783925153
    },
    {
      "model": "sequence_dynamic_prototype",
      "stage": "source_val",
      "source": "amazon_movies_and_tv",
      "target": "",
      "seed": 2026,
      "semantic_checkpoint": "artifacts\\checkpoints\\semantic_final\\semantic_amazon_movies_and_tv_seed2026.pt",
      "prototype_bank": "artifacts\\prototypes\\sequence_dynamic_amazon_movies_and_tv_M128_seed2026.pt",
      "candidate_dynamic_source": "artifacts\\checkpoints\\continuous_dynamic\\semantic_conditioned_prior_enhanced_amazon_movies_and_tv_seed2026.pt::enhanced",
      "ranking_mode": "sampled",
      "eval_negatives": 100,
      "Recall@10": 0.3672351265963601,
      "Recall@20": 0.40866261736305787,
      "NDCG@10": 0.25269263982772827,
      "NDCG@20": 0.2632458508014679,
      "MRR@10": 0.21692271530628204,
      "MRR@20": 0.21986110508441925,
      "tie_case_ratio": 0.4589062430472122,
      "all_equal_ratio": 0.0,
      "avg_tie_items": 13.515329506518933,
      "num_eval_users": 179784,
      "tie_policy": "worst",
      "beta_sem": 0.2,
      "beta_dyn": 0.1,
      "top_m": 16,
      "temperature": 0.05,
      "semantic_score_norm": "zscore",
      "prototype_score_norm": "zscore",
      "dynamic_score_norm": "zscore",
      "eval_elapsed_sec": 36.46917939186096,
      "eval_users_per_sec": 4929.751724551374
    },
    {
      "model": "sequence_dynamic_prototype",
      "stage": "source_val",
      "source": "amazon_movies_and_tv",
      "target": "",
      "seed": 2026,
      "semantic_checkpoint": "artifacts\\checkpoints\\semantic_final\\semantic_amazon_movies_and_tv_seed2026.pt",
      "prototype_bank": "artifacts\\prototypes\\sequence_dynamic_amazon_movies_and_tv_M128_seed2026.pt",
      "candidate_dynamic_source": "artifacts\\checkpoints\\continuous_dynamic\\semantic_conditioned_prior_enhanced_amazon_movies_and_tv_seed2026.pt::enhanced",
      "ranking_mode": "sampled",
      "eval_negatives": 100,
      "Recall@10": 0.36759110933119743,
      "Recall@20": 0.40938014506296444,
      "NDCG@10": 0.2524113953113556,
      "NDCG@20": 0.263058602809906,
      "MRR@10": 0.2164519876241684,
      "MRR@20": 0.2194177508354187,
      "tie_case_ratio": 0.45896186534953054,
      "all_equal_ratio": 0.0,
      "avg_tie_items": 13.510940906866017,
      "num_eval_users": 179784,
      "tie_policy": "worst",
      "beta_sem": 0.2,
      "beta_dyn": 0.15,
      "top_m": 16,
      "temperature": 0.05,
      "semantic_score_norm": "zscore",
      "prototype_score_norm": "zscore",
      "dynamic_score_norm": "zscore",
      "eval_elapsed_sec": 36.53337073326111,
      "eval_users_per_sec": 4921.089852689643
    },
    {
      "model": "sequence_dynamic_prototype",
      "stage": "source_val",
      "source": "amazon_movies_and_tv",
      "target": "",
      "seed": 2026,
      "semantic_checkpoint": "artifacts\\checkpoints\\semantic_final\\semantic_amazon_movies_and_tv_seed2026.pt",
      "prototype_bank": "artifacts\\prototypes\\sequence_dynamic_amazon_movies_and_tv_M128_seed2026.pt",
      "candidate_dynamic_source": "artifacts\\checkpoints\\continuous_dynamic\\semantic_conditioned_prior_enhanced_amazon_movies_and_tv_seed2026.pt::enhanced",
      "ranking_mode": "sampled",
      "eval_negatives": 100,
      "Recall@10": 0.3673352467405331,
      "Recall@20": 0.40966381880478797,
      "NDCG@10": 0.25160813331604004,
      "NDCG@20": 0.2623944878578186,
      "MRR@10": 0.21549370884895325,
      "MRR@20": 0.21849915385246277,
      "tie_case_ratio": 0.4588283718239665,
      "all_equal_ratio": 0.0,
      "avg_tie_items": 13.50718640145953,
      "num_eval_users": 179784,
      "tie_policy": "worst",
      "beta_sem": 0.2,
      "beta_dyn": 0.2,
      "top_m": 16,
      "temperature": 0.05,
      "semantic_score_norm": "zscore",
      "prototype_score_norm": "zscore",
      "dynamic_score_norm": "zscore",
      "eval_elapsed_sec": 36.5006308555603,
      "eval_users_per_sec": 4925.503910095096
    }
  ],
  "protocol": {
    "checkpoint_selection": "source_validation_only",
    "target_usage": "none_during_tuning"
  }
}